odoo/addons/shopfloor_manual_product_transfer_mobile/README.rst
odoo/addons/shopfloor_manual_product_transfer_mobile/__init__.py
odoo/addons/shopfloor_manual_product_transfer_mobile/__manifest__.py
odoo/addons/shopfloor_manual_product_transfer_mobile/i18n/it.po
odoo/addons/shopfloor_manual_product_transfer_mobile/i18n/pt_BR.po
odoo/addons/shopfloor_manual_product_transfer_mobile/i18n/shopfloor_manual_product_transfer_mobile.pot
odoo/addons/shopfloor_manual_product_transfer_mobile/readme/CONTRIBUTORS.rst
odoo/addons/shopfloor_manual_product_transfer_mobile/readme/DESCRIPTION.rst
odoo/addons/shopfloor_manual_product_transfer_mobile/static/description/icon.png
odoo/addons/shopfloor_manual_product_transfer_mobile/static/description/index.html
odoo/addons/shopfloor_manual_product_transfer_mobile/static/wms/src/demo/demo.manual_product_transfer.js
odoo/addons/shopfloor_manual_product_transfer_mobile/static/wms/src/scenario/manual_product_transfer.js
odoo/addons/shopfloor_manual_product_transfer_mobile/templates/assets.xml
odoo14_addon_shopfloor_manual_product_transfer_mobile-14.0.1.3.1.dist-info/METADATA
odoo14_addon_shopfloor_manual_product_transfer_mobile-14.0.1.3.1.dist-info/WHEEL
odoo14_addon_shopfloor_manual_product_transfer_mobile-14.0.1.3.1.dist-info/top_level.txt
odoo14_addon_shopfloor_manual_product_transfer_mobile-14.0.1.3.1.dist-info/RECORD
