Metadata-Version: 2.1
Name: odoo14-addon-shopfloor-manual-product-transfer-mobile
Version: 14.0.1.3.1
Summary: Frontend for manual product transfer scenario for Shopfloor
Home-page: https://github.com/OCA/wms
Author: Camptocamp, Odoo Community Association (OCA)
Author-email: support@odoo-community.org
License: AGPL-3
Platform: UNKNOWN
Classifier: Programming Language :: Python
Classifier: Framework :: Odoo
Classifier: Framework :: Odoo :: 14.0
Classifier: License :: OSI Approved :: GNU Affero General Public License v3
Classifier: Development Status :: 3 - Alpha
Requires-Python: >=3.6
Requires-Dist: odoo14-addon-shopfloor-manual-product-transfer
Requires-Dist: odoo14-addon-shopfloor-mobile
Requires-Dist: odoo <14.1dev,>=14.0a
